naga_gwas-0.4.1.post2.dist-info/METADATA
naga_gwas-0.4.1.post2.dist-info/RECORD
naga_gwas-0.4.1.post2.dist-info/WHEEL
naga_gwas-0.4.1.post2.dist-info/top_level.txt
nbgwas/__init__.py
nbgwas/nbgwas.py
nbgwas/network.py
nbgwas/propagation.py
nbgwas/tables.py
nbgwas/utils.py
nbgwas/version.py
