Metadata-Version: 2.1
Name: naga-gwas
Version: 0.4.1.post2
Summary: Network Assisted Genomic Association
Home-page: https://github.com/shfong/naga
Author: Samson Fong
Author-email: shfong@ucsd.edu
License: MIT
Platform: UNKNOWN
Classifier: Development Status :: 2 - Pre-Alpha
Classifier: Intended Audience :: Science/Research
Classifier: Topic :: Software Development :: Build Tools
Classifier: License :: OSI Approved :: MIT License
Classifier: Programming Language :: Python :: 3.6
Classifier: Programming Language :: Python :: 3.7
Requires-Dist: ijson
Requires-Dist: requests
Requires-Dist: pytz (>=2011k)
Requires-Dist: cycler (>=0.10)
Requires-Dist: kiwisolver (>=1.0.1)
Requires-Dist: pyparsing (!=2.0.4,!=2.1.2,!=2.1.6,>=2.0.1)
Requires-Dist: pytz
Requires-Dist: networkx (==1.11)
Requires-Dist: numpy
Requires-Dist: matplotlib
Requires-Dist: pandas (>=0.23.0)
Requires-Dist: scipy
Requires-Dist: seaborn
Requires-Dist: ndex2
Requires-Dist: python-igraph
Requires-Dist: py2cytoscape
Requires-Dist: coverage
Requires-Dist: pytest
Requires-Dist: mygene
Requires-Dist: scikit-learn
Requires-Dist: sphinx
